README.rst
setup.py
pymongorm/__init__.py
pymongorm/basemodel.py
pymongorm/connection.py
pymongorm/exception.py
pymongorm/field.py
pymongorm.egg-info/PKG-INFO
pymongorm.egg-info/SOURCES.txt
pymongorm.egg-info/dependency_links.txt
pymongorm.egg-info/top_level.txt
pymongorm.egg-info/zip-safe