Metadata-Version: 1.1
Name: pymongorm
Version: 0.0.3
Summary: a package use orm to operate mongo
Home-page: http://github.com/wupengxin/mongorm
Author: wupengxin
Author-email: 15645060726@163.com
License: MIT
Keywords: mongo python orm
Platform: UNKNOWN
Classifier: License :: OSI Approved :: MIT License
Classifier: Programming Language :: Python
Classifier: Intended Audience :: Developers
Classifier: Operating System :: OS Independent
